README.md
pyproject.toml
setup.py
src/exodo.py
src/log.py
src/master.py
src/raw.py
src/core/__init__.py
src/core/conexion.py
src/core/core.py
src/core/utility.py
src/int/__init__.py
src/int/mail.py
src/mifra.egg-info/PKG-INFO
src/mifra.egg-info/SOURCES.txt
src/mifra.egg-info/dependency_links.txt
src/mifra.egg-info/top_level.txt