Metadata-Version: 2.1
Name: mifra
Version: 0.3.6
Summary: Un package hacer migraciones
Home-page: https://github.com/felipeals256/mifra
Author: Felipe Leiva
Author-email: anexatec@gmail.com
License: MIT
Platform: UNKNOWN
